<annotation>
	<folder>banheng</folder>
	<filename>208-142.jpg</filename>
	<path>D:\banheng\208-142.jpg</path>
	<source>
		<database>Unknown</database>
	</source>
	<size>
		<width>0</width>
		<height>0</height>
		<depth>3</depth>
	</size>
	<segmented>0</segmented>
	<object>
		<name>dog</name>
		<pose>Unspecified</pose>
		<truncated>0</truncated>
		<difficult>0</difficult>
		<bndbox>
			<xmin>114</xmin>
			<ymin>24</ymin>
			<xmax>535</xmax>
			<ymax>348</ymax>
		</bndbox>
	</object>
</annotation>
