<annotation>
	<folder>banheng</folder>
	<filename>208-37.jpg</filename>
	<path>D:\banheng\208-37.jpg</path>
	<source>
		<database>Unknown</database>
	</source>
	<size>
		<width>3691</width>
		<height>2413</height>
		<depth>3</depth>
	</size>
	<segmented>0</segmented>
	<object>
		<name>dog</name>
		<pose>Unspecified</pose>
		<truncated>0</truncated>
		<difficult>0</difficult>
		<bndbox>
			<xmin>156</xmin>
			<ymin>273</ymin>
			<xmax>1928</xmax>
			<ymax>1424</ymax>
		</bndbox>
	</object>
	<object>
		<name>dog</name>
		<pose>Unspecified</pose>
		<truncated>0</truncated>
		<difficult>0</difficult>
		<bndbox>
			<xmin>2149</xmin>
			<ymin>1011</ymin>
			<xmax>3538</xmax>
			<ymax>1968</ymax>
		</bndbox>
	</object>
</annotation>
