<annotation>
	<folder>banheng</folder>
	<filename>650-467.jpg</filename>
	<path>D:\banheng\650-467.jpg</path>
	<source>
		<database>Unknown</database>
	</source>
	<size>
		<width>4032</width>
		<height>3024</height>
		<depth>3</depth>
	</size>
	<segmented>0</segmented>
	<object>
		<name>dog</name>
		<pose>Unspecified</pose>
		<truncated>0</truncated>
		<difficult>0</difficult>
		<bndbox>
			<xmin>1250</xmin>
			<ymin>457</ymin>
			<xmax>2859</xmax>
			<ymax>2789</ymax>
		</bndbox>
	</object>
	<object>
		<name>dog</name>
		<pose>Unspecified</pose>
		<truncated>0</truncated>
		<difficult>0</difficult>
		<bndbox>
			<xmin>3127</xmin>
			<ymin>1450</ymin>
			<xmax>3411</xmax>
			<ymax>1763</ymax>
		</bndbox>
	</object>
	<object>
		<name>dog</name>
		<pose>Unspecified</pose>
		<truncated>0</truncated>
		<difficult>0</difficult>
		<bndbox>
			<xmin>733</xmin>
			<ymin>1708</ymin>
			<xmax>979</xmax>
			<ymax>1950</ymax>
		</bndbox>
	</object>
</annotation>
