<annotation>
	<folder>ScoreDataset</folder>
	<filename>943-276.jpg</filename>
	<path>D:\banheng\ScoreDataset\943-276.jpg</path>
	<source>
		<database>Unknown</database>
	</source>
	<size>
		<width>5152</width>
		<height>3864</height>
		<depth>3</depth>
	</size>
	<segmented>0</segmented>
	<object>
		<name>dog</name>
		<pose>Unspecified</pose>
		<truncated>0</truncated>
		<difficult>0</difficult>
		<bndbox>
			<xmin>1532</xmin>
			<ymin>1023</ymin>
			<xmax>3903</xmax>
			<ymax>2711</ymax>
		</bndbox>
	</object>
	<object>
		<name>dog</name>
		<pose>Unspecified</pose>
		<truncated>0</truncated>
		<difficult>0</difficult>
		<bndbox>
			<xmin>1182</xmin>
			<ymin>603</ymin>
			<xmax>1961</xmax>
			<ymax>982</ymax>
		</bndbox>
	</object>
</annotation>
