<annotation>
	<folder>ScoreDataset</folder>
	<filename>943-110.jpg</filename>
	<path>D:\banheng\ScoreDataset\943-110.jpg</path>
	<source>
		<database>Unknown</database>
	</source>
	<size>
		<width>5152</width>
		<height>3864</height>
		<depth>3</depth>
	</size>
	<segmented>0</segmented>
	<object>
		<name>dog</name>
		<pose>Unspecified</pose>
		<truncated>0</truncated>
		<difficult>0</difficult>
		<bndbox>
			<xmin>2316</xmin>
			<ymin>1610</ymin>
			<xmax>3041</xmax>
			<ymax>1894</ymax>
		</bndbox>
	</object>
	<object>
		<name>dog</name>
		<pose>Unspecified</pose>
		<truncated>0</truncated>
		<difficult>0</difficult>
		<bndbox>
			<xmin>2682</xmin>
			<ymin>2073</ymin>
			<xmax>3107</xmax>
			<ymax>2394</ymax>
		</bndbox>
	</object>
	<object>
		<name>dog</name>
		<pose>Unspecified</pose>
		<truncated>0</truncated>
		<difficult>0</difficult>
		<bndbox>
			<xmin>2345</xmin>
			<ymin>2577</ymin>
			<xmax>2899</xmax>
			<ymax>2802</ymax>
		</bndbox>
	</object>
</annotation>
